django_watchlist-0.4.0.dist-info/METADATA
django_watchlist-0.4.0.dist-info/RECORD
django_watchlist-0.4.0.dist-info/WHEEL
django_watchlist-0.4.0.dist-info/top_level.txt
watchlist/__init__.py
watchlist/admin.py
watchlist/models.py
watchlist/urls.py
watchlist/views.py
watchlist/templates/watchlist/watch_item_added.html
watchlist/templates/watchlist/watch_item_removed.html
watchlist/templates/watchlist/watch_list.html
