Metadata-Version: 2.1
Name: django-watchlist
Version: 0.4.0
Summary: Stupid simple django watch and favorite
Home-page: http://github.com/tBaxter/django-watchlist
Author: Tim Baxter
Author-email: mail.baxter@gmail.com
License: LICENSE
Platform: UNKNOWN
